XYunA.v
// Yung Cheng, Adrian U. (S14)
/*
    Boolean Function Assigned
    F = (AB' + A'B)(C + D')
*/

module YungCheng(A, B, C, D, F);
    input A, B, C, D;
    output F;

    assign F = (A & ~B | ~A & B) & (C | ~D);
endmodule

XYunA_tb.v
// Yung Cheng, Adrian U. (S14)
/*
    Boolean Function Assigned
    F = (AB' + A'B)(C + D')
*/

module YungCheng_tb();
    reg [3:0] t_in;
    wire t_out;

    YungCheng dut(t_in[3], t_in[2], t_in[1], t_in[0], t_out);

    initial begin
        t_in = 4'b0000;
        repeat(16)
            #10 t_in += 4'b0001;
    end

    initial begin
        $display("Written by Adrian Yung Cheng - S14");
        $display("Boolean Function Assigned:");
        $display("F = (AB' + A'B)(C + D')");
        $display("Verilog Dataflow Model");
        $display("Time  |   A   |   B   |   C   |   D   |   F");
        $monitor("%03d   |   %b   |   %b   |   %b   |   %b   |   %b", $time, t_in[3], t_in[2], t_in[1], t_in[0], t_out);
        $dumpfile("XYunA_dump.vcd");
        $dumpvars();
    end

endmodule

XYunA_dump.vcd
$date
	Wed Jun 14 00:55:42 2023
$end
$version
	Icarus Verilog
$end
$timescale
	1s
$end
$scope module YungCheng_tb $end
$var wire 1 ! t_out $end
$var reg 4 " t_in [3:0] $end
$scope module dut $end
$var wire 1 # A $end
$var wire 1 $ B $end
$var wire 1 % C $end
$var wire 1 & D $end
$var wire 1 ! F $end
$upscope $end
$upscope $end
$enddefinitions $end
$comment Show the parameter values. $end
$dumpall
$end
#0
$dumpvars
0&
0%
0$
0#
b0 "
0!
$end
#10
1&
b1 "
#20
1%
0&
b10 "
#30
1&
b11 "
#40
1!
1$
0%
0&
b100 "
#50
0!
1&
b101 "
#60
1!
1%
0&
b110 "
#70
1&
b111 "
#80
1#
0$
0%
0&
b1000 "
#90
0!
1&
b1001 "
#100
1!
1%
0&
b1010 "
#110
1&
b1011 "
#120
0!
1$
0%
0&
b1100 "
#130
1&
b1101 "
#140
1%
0&
b1110 "
#150
1&
b1111 "
#160
0#
0$
0%
0&
b0 "
